midb/__init__.py
midb/constants.py
midb/backend/__init__.py
midb/backend/_db_creation_and_validation.py
midb/backend/_run_sql.py
midb/backend/_serialization.py
midb/persistent_objects/__init__.py
midb/persistent_objects/_basepersistentobject.py
midb/persistent_objects/_pdict.py
midb/persistent_objects/_persistentsequence.py
midb/persistent_objects/_plist.py
midb/persistent_objects/_pobject.py
midb/persistent_objects/_ptuple.py
midb-0.5.1.dist-info/LICENSE
midb-0.5.1.dist-info/METADATA
midb-0.5.1.dist-info/WHEEL
midb-0.5.1.dist-info/top_level.txt
midb-0.5.1.dist-info/RECORD
