Metadata-Version: 2.1
Name: midb
Version: 0.5.1
Summary: Mostly Invisible Database. A database access layer that acts like python in-memory objects.
Home-page: https://gitlab.com/gossrock/midb
Author: Peter Goss
Author-email: gossrock@gmail.com
License: UNKNOWN
Project-URL: Bug Tracker, https://gitlab.com/gossrock/midb/-/issues
Platform: UNKNOWN
Classifier: Programming Language :: Python :: 3
Classifier: License :: OSI Approved :: MIT License
Classifier: Operating System :: OS Independent
Requires-Python: >=3.8
License-File: LICENSE
